complete_numbers/__init__.py
complete_numbers/ctn.py
complete_numbers-0.0.5.dist-info/METADATA
complete_numbers-0.0.5.dist-info/WHEEL
complete_numbers-0.0.5.dist-info/licenses/LICENSE
complete_numbers-0.0.5.dist-info/RECORD
