Metadata-Version: 2.4
Name: complete_numbers
Version: 0.0.5
Summary: Simple library to test the arithmetical properties of a number system allowing for zero division
Project-URL: Homepage, https://github.com/evensong/complete_numbers
Project-URL: Issues, https://github.com/evensong/complete_numbers/issues
Author-email: Ben Haws <benjamin.haws216@gmail.com>
License-Expression: Apache-2.0
License-File: LICENSE
Classifier: Operating System :: OS Independent
Classifier: Programming Language :: Python :: 3
Requires-Python: >=3.9
